ubii/cli/__init__.py
ubii/cli/main.py
ubii/framework/__init__.py
ubii/framework/client.py
ubii/framework/constants.py
ubii/framework/errors.py
ubii/framework/logging.py
ubii/framework/processing.py
ubii/framework/protocol.py
ubii/framework/py.typed
ubii/framework/services.py
ubii/framework/topics.py
ubii/framework/util/__init__.py
ubii/framework/util/collections.py
ubii/framework/util/enum.py
ubii/framework/util/functools.py
ubii/framework/util/logging_config.yaml
ubii/framework/util/typing.py
ubii/node/__init__.py
ubii/node/connect.py
ubii/node/connections.py
ubii/node/protocol.py
ubii/node/pytest/__init__.py
ubii_node_python-0.3.0.dist-info/LICENSE.rst
ubii_node_python-0.3.0.dist-info/METADATA
ubii_node_python-0.3.0.dist-info/WHEEL
ubii_node_python-0.3.0.dist-info/entry_points.txt
ubii_node_python-0.3.0.dist-info/top_level.txt
ubii_node_python-0.3.0.dist-info/RECORD
