Metadata-Version: 2.1
Name: ubii-node-python
Version: 0.3.0
Summary: Ubi Interact Python Node
Home-page: https://github.com/saggitar/ubii-node-python.git
Author: Maximilian Schmidt
Author-email: ga97lul@mytum.de
Keywords: ubi-interact,ubii,distributed,vr,augmented
Classifier: Programming Language :: Python :: 3
Requires-Python: >=3.7
License-File: LICENSE.rst
Requires-Dist: ubii-message-formats (>=0.3.0)
Requires-Dist: codestare-async-utils (>=0.2.0)
Requires-Dist: pyyaml
Requires-Dist: aiohttp
Requires-Dist: importlib-metadata ; python_version < "3.8"
Requires-Dist: backports.cached-property ; python_version < "3.8"
Requires-Dist: typing-extensions ; python_version < "3.8"
Provides-Extra: cli
Requires-Dist: argparse (==1.4.0) ; extra == 'cli'
Provides-Extra: dev
Requires-Dist: setuptools-changelog (==1.0.0) ; extra == 'dev'
Provides-Extra: docs
Requires-Dist: sphinx (==5.0.2) ; extra == 'docs'
Provides-Extra: test
Requires-Dist: pytest (==7.1.2) ; extra == 'test'
Requires-Dist: pytest-asyncio (==0.18.3) ; extra == 'test'
Requires-Dist: pandas ; extra == 'test'
